TrackCobra/Agent.py
TrackCobra/Logged.py
TrackCobra/Server.py
TrackCobra/Tele.py
TrackCobra/Users.py
TrackCobra/Validator.py
TrackCobra/Who.py
TrackCobra/__init__.py
TrackCobra/Html5/PyHtml.py
TrackCobra/Html5/__init__.py
TrackCobra-0.3.0.dist-info/LICENSE
TrackCobra-0.3.0.dist-info/METADATA
TrackCobra-0.3.0.dist-info/WHEEL
TrackCobra-0.3.0.dist-info/top_level.txt
TrackCobra-0.3.0.dist-info/RECORD
