Metadata-Version: 2.1
Name: TrackCobra
Version: 0.3.0
Summary: Short EveryThing In Seconds
Home-page: https://github.com/MrGps1
Author: Mr GPS
Author-email: MrGps00@gmail.com
Project-URL: Bug Tracker, https://github.com/MrGps1/TrackCobra
Classifier: Programming Language :: Python :: 3
Classifier: License :: OSI Approved :: MIT License
Classifier: Operating System :: OS Independent
Requires-Python: >=3.9
License-File: LICENSE
